ExtraUtils/RateLimit.py
ExtraUtils/__init__.py
ExtraUtils/asyncKeys.py
ExtraUtils/asyncThreads.py
ExtraUtils/asyncTokens.py
ExtraUtils/callbackVoid.py
ExtraUtils/getFileContent.py
ExtraUtils/timeBasedToken.py
ExtraUtils/validate_dict.py
extrautilities-2.1.dist-info/METADATA
extrautilities-2.1.dist-info/WHEEL
extrautilities-2.1.dist-info/top_level.txt
extrautilities-2.1.dist-info/RECORD
