Metadata-Version: 2.1
Name: extrautilities
Version: 2.1
Summary: This package provides a few extra utilities for Python, like Asyncronus Encryption/Decryption.
Home-page: https://github.com/RandomTimeLP/ExtraUtils
Author: RandomTimeTV
Author-email: dergepanzerte1@gmail.com
License: Unlicensed
Keywords: RateLimit,timeBasedToken,getFileContent,callbackVoid,validate_dict
Classifier: Development Status :: 3 - Alpha
Classifier: License :: OSI Approved :: MIT License
Classifier: Programming Language :: Python :: 3.6
Classifier: Programming Language :: Python :: 3.7
Classifier: Programming Language :: Python :: 3.8
Classifier: Programming Language :: Python :: 3.9
Classifier: Programming Language :: Python :: 3.10
Classifier: Programming Language :: Python :: 3.11
Classifier: Programming Language :: Python :: 3.12
Requires-Dist: extradecorators
Requires-Dist: cryptography
Requires-Dist: pycryptodome
